LICENSE.md
MANIFEST.in
README.md
ez_setup.py
setup.cfg
setup.py
Equation/__init__.py
Equation/_info.py
Equation/core.py
Equation/equation_base.py
Equation/equation_scipy.py
Equation/similar.py
Equation/util.py
Equation.egg-info/PKG-INFO
Equation.egg-info/SOURCES.txt
Equation.egg-info/dependency_links.txt
Equation.egg-info/not-zip-safe
Equation.egg-info/requires.txt
Equation.egg-info/top_level.txt
sample/DPOF.py
sample/dataset.hdf5
tests/__init__.py
tests/test_Equation.py