Metadata-Version: 1.1
Name: Equation
Version: 1.2
Summary: General Equation Parser and Evaluator
Home-page: https://github.com/alphaomega-technology/Equation
Author: Glen Fletcher
Author-email: glen.fletcher@alphaomega-technology.com.au
License: AlphaOmega Technology Open License Version 1.0 (http://www.alphaomega-technology.com.au/license/AOT-OL/1.0)
Platform: UNKNOWN
Classifier: Development Status :: 5 - Production/Stable
Classifier: Intended Audience :: Science/Research
Classifier: Intended Audience :: Developers
Classifier: Operating System :: OS Independent
Classifier: Topic :: Scientific/Engineering :: Mathematics
Classifier: Natural Language :: English
Classifier: Programming Language :: Python :: 2
Classifier: Programming Language :: Python :: 2.6
Classifier: Programming Language :: Python :: 2.7
Classifier: Programming Language :: Python :: 3
Classifier: Programming Language :: Python :: 3.3
Classifier: Programming Language :: Python :: 3.4
